mingdongnlp/__init__.py
mingdongnlp/version.py
mingdongnlp/callbacks/__init__.py
mingdongnlp/callbacks/fine_csv_logger.py
mingdongnlp/common/__init__.py
mingdongnlp/common/component.py
mingdongnlp/common/constant.py
mingdongnlp/common/document.py
mingdongnlp/common/structure.py
mingdongnlp/common/transform.py
mingdongnlp/common/trie.py
mingdongnlp/common/vocab.py
mingdongnlp/components/__init__.py
mingdongnlp/components/lambda_wrapper.py
mingdongnlp/components/ner.py
mingdongnlp/components/pipeline.py
mingdongnlp/components/pos.py
mingdongnlp/components/rnn_language_model.py
mingdongnlp/components/tok.py
mingdongnlp/components/classifiers/__init__.py
mingdongnlp/components/classifiers/transformer_classifier.py
mingdongnlp/components/parsers/__init__.py
mingdongnlp/components/parsers/alg.py
mingdongnlp/components/parsers/biaffine_parser.py
mingdongnlp/components/parsers/conll.py
mingdongnlp/components/parsers/biaffine/__init__.py
mingdongnlp/components/parsers/biaffine/layers.py
mingdongnlp/components/parsers/biaffine/model.py
mingdongnlp/components/taggers/__init__.py
mingdongnlp/components/taggers/cnn_tagger.py
mingdongnlp/components/taggers/rnn_tagger.py
mingdongnlp/components/taggers/tagger.py
mingdongnlp/components/taggers/ngram_conv/__init__.py
mingdongnlp/components/taggers/ngram_conv/ngram_conv_tagger.py
mingdongnlp/components/taggers/transformers/__init__.py
mingdongnlp/components/taggers/transformers/metrics.py
mingdongnlp/components/taggers/transformers/transformer_tagger.py
mingdongnlp/components/taggers/transformers/transformer_transform.py
mingdongnlp/components/taggers/transformers/utils.py
mingdongnlp/datasets/__init__.py
mingdongnlp/datasets/glue.py
mingdongnlp/datasets/classification/__init__.py
mingdongnlp/datasets/classification/sentiment.py
mingdongnlp/datasets/cws/__init__.py
mingdongnlp/datasets/cws/ctb.py
mingdongnlp/datasets/cws/sighan2005/__init__.py
mingdongnlp/datasets/cws/sighan2005/msr.py
mingdongnlp/datasets/cws/sighan2005/pku.py
mingdongnlp-2.0.0a42.dist-info/LICENSE
mingdongnlp-2.0.0a42.dist-info/METADATA
mingdongnlp-2.0.0a42.dist-info/WHEEL
mingdongnlp-2.0.0a42.dist-info/top_level.txt
mingdongnlp-2.0.0a42.dist-info/RECORD
